odoo10_addon_base_vat_optional_vies-10.0.1.0.0-py2.7-nspkg.pth
odoo/addons/base_vat_optional_vies/README.rst
odoo/addons/base_vat_optional_vies/__init__.py
odoo/addons/base_vat_optional_vies/__manifest__.py
odoo/addons/base_vat_optional_vies/i18n/.gitkeep
odoo/addons/base_vat_optional_vies/i18n/es.po
odoo/addons/base_vat_optional_vies/models/__init__.py
odoo/addons/base_vat_optional_vies/models/res_partner.py
odoo/addons/base_vat_optional_vies/static/description/icon.png
odoo/addons/base_vat_optional_vies/tests/__init__.py
odoo/addons/base_vat_optional_vies/tests/test_res_partner.py
odoo/addons/base_vat_optional_vies/views/res_partner_view.xml
odoo10_addon_base_vat_optional_vies-10.0.1.0.0.dist-info/DESCRIPTION.rst
odoo10_addon_base_vat_optional_vies-10.0.1.0.0.dist-info/METADATA
odoo10_addon_base_vat_optional_vies-10.0.1.0.0.dist-info/RECORD
odoo10_addon_base_vat_optional_vies-10.0.1.0.0.dist-info/WHEEL
odoo10_addon_base_vat_optional_vies-10.0.1.0.0.dist-info/metadata.json
odoo10_addon_base_vat_optional_vies-10.0.1.0.0.dist-info/namespace_packages.txt
odoo10_addon_base_vat_optional_vies-10.0.1.0.0.dist-info/top_level.txt
